<?xml version="1.0" encoding="utf-8"?>
  <!--
    Created with Liquid XML Studio Developer Edition (Education)
    8.0.10.2115 (http://www.liquid-technologies.com)
  -->
<coordinateTransformationInfoResponse
  xmlns:gml="http://www.opengis.net/gml/3.2" xmlns:xlink="http://www.w3.org/1999/xlink"
  xmlns:gmd="http://www.isotc211.org/2005/gmd" xmlns:gco="http://www.isotc211.org/2005/gco"
  xmlns:gss="http://www.isotc211.org/2005/gss" xmlns:gts="http://www.isotc211.org/2005/gts"
  xmlns:gsr="http://www.isotc211.org/2005/gsr" xmlns:xsi="http://www.w3.org/2001/XMLSchema-instance">
  <queryInfo>
    <timeCreated>1978-02-03T11:37:55.52</timeCreated>
    <queryUrl>http://www.liquid-technologies.com</queryUrl>
  </queryInfo>
  <coordinateTransformationInfo>
    <coordinateTransformation order="-1339"
      code="string" hub="string" inputSrsCode="string" targetSrsCode="string"
      accuracy="6436.21491" />
    <coordinateTransformation order="-5060"
      code="string" hub="string" inputSrsCode="string" targetSrsCode="string"
      accuracy="1847.89491" />
  </coordinateTransformationInfo>
</coordinateTransformationInfoResponse>
